{"slug": "boethius", "person_name": "Boethius", "person_name_full": "Boethius", "aliases": [], "person_religion": "christian", "majority_tradition": "christian", "display_tradition": "christian", "religious_tradition": "", "social_role": "philosopher", "gender": "male", "historicity": "historical", "approx_century": "6 CE", "birth_year_approx": 477, "death_year_approx": 524, "notes": "Roman philosopher and statesman, author of The Consolation of Philosophy, executed by King Theoderic.", "collections": ["cassiodorus", "ennodius_pavia"], "n_docs": 2, "n_collections": 2, "n_adjectives_external_total": 2.0, "n_adjectives_external_unique": 2, "trait_descriptors_external": {"learned": 1.0, "intellectual": 1.0}, "described_by": {"learned": ["Cassiodorus"], "intellectual": ["Ennodius of Pavia"]}, "docs": [{"doc_id": "roman_letters_cassiodorus_2584", "title": "Letter 1045", "author": "Cassiodorus", "year": 522, "religion": "christian", "period": "Ostrogothic / Early Byzantine", "subject_summary": "Book 1, Letter XLV: BOETHIO V. I. PATRICIO", "excerpt": "We have learned that you, nourished by extensive learning, know these arts so well that while the uneducated practice them mechanically, you have drunk from the very fountain of the disciplines."}, {"doc_id": "roman_letters_ennodius_pavia_3269", "title": "Letter 8036", "author": "Ennodius of Pavia", "year": 520, "religion": "christian", "period": "Ostrogothic / Early Byzantine", "subject_summary": "", "excerpt": "… others take for granted: that your intellectual gifts are a public good, not merely a private accomplishment. May they continue to serve both you and the world. Farewell."}], "lda_pagan": null, "lda_christian": {"loadings": {"topic_0": 0.1117, "topic_1": 0.1172, "topic_2": 0.7711}, "loadings_smoothed_external": {"topic_0": 0.1117, "topic_1": 0.1172, "topic_2": 0.7711}, "dominant_topic_external": 2, "dominant_label_external": "Asceticism"}, "has_portrait": true}