{"slug": "polycarp", "person_name": "Polycarp", "person_name_full": "Polycarp", "aliases": [], "person_religion": "christian", "majority_tradition": "christian", "display_tradition": "christian", "religious_tradition": "", "social_role": "bishop", "gender": "male", "historicity": "historical", "approx_century": "2 CE", "birth_year_approx": 69, "death_year_approx": 155, "notes": "Bishop of Smyrna, early Christian martyr known for his steadfast faith and confrontation with Roman authorities.", "collections": ["eusebius_history", "martyrdom_polycarp"], "n_docs": 2, "n_collections": 2, "n_adjectives_external_total": 6.0, "n_adjectives_external_unique": 6, "trait_descriptors_external": {"trustworthy": 1.0, "quiet": 1.0, "unshaken": 1.0, "godly": 1.0, "virtuous": 1.0, "blameless": 1.0}, "described_by": {"trustworthy": ["Eusebius"], "quiet": ["Eusebius"], "unshaken": ["Eusebius"], "godly": ["Eusebius"], "virtuous": ["Eusebius"], "blameless": ["Church of Smyrna"]}, "docs": [{"doc_id": "eusebius_history_ch_4", "title": "Ecclesiastical History, Book 4", "author": "Eusebius", "year": 313, "religion": "christian", "period": "Late Empire (Constantinian)", "subject_summary": "", "excerpt": "… continued undisturbed, preserved a quiet and unshaken mind , and determined to remain in the city. But being persuaded by his friends who entreated and exhorted him to retire secretly, he went out to a farm not far distant from the city and abode there with a few companions, night and day"}, {"doc_id": "martyrdom_polycarp_ch_1", "title": "Martyrdom of Polycarp", "author": "Church of Smyrna", "year": 156, "religion": "christian", "period": "Principate", "subject_summary": "", "excerpt": "… his martyrdom , and [considered] the blameless life he had led from the beginning, and how he was now crowned with the wreath of immortality , having beyond dispute received his reward, he did his utmost that not the least memorial of him should be taken away by us, although many desired to do"}], "lda_pagan": null, "lda_christian": {"loadings": {"topic_0": 0.2509, "topic_1": 0.0484, "topic_2": 0.7007}, "loadings_smoothed_external": {"topic_0": 0.2509, "topic_1": 0.0484, "topic_2": 0.7007}, "dominant_topic_external": 2, "dominant_label_external": "Asceticism"}, "has_portrait": true}